sclogging/__init__.py
sclogging/config.py
sclogging/sclogging_main.py
sclogging/settings.toml
sclogging-1.1.0.dist-info/licenses/LICENSE
sclogging-1.1.0.dist-info/METADATA
sclogging-1.1.0.dist-info/WHEEL
sclogging-1.1.0.dist-info/top_level.txt
sclogging-1.1.0.dist-info/RECORD
