Metadata-Version: 2.4
Name: sclogging
Version: 1.1.0
Summary: A Python module (with the help of coloredlogs) to add color to logs.
Home-page: https://github.com/sshimek42/sclogging
Author: 
Author-email: 
License-Expression: MIT
Project-URL: Homepage, https://github.com/sshimek42/sclogging
Project-URL: Documentation, https://sclogging.readthedocs.io/
Classifier: Programming Language :: Python :: 3
Classifier: Operating System :: OS Independent
Requires-Python: >=3.13
License-File: LICENSE
Requires-Dist: dynaconf>=3.2.12
Requires-Dist: colorama>=0.4.5
Requires-Dist: coloredlogs>=15.0.1
Requires-Dist: PyInputPlus>=0.2.12
Requires-Dist: setuptools>=80.9.0
Dynamic: home-page
Dynamic: license-file
